power_dict/__init__.py
power_dict/errors.py
power_dict/internal_validators.py
power_dict/schema_validator.py
power_dict/utils.py
tests/__init__.py
tests/get_bool_dict_property_tests.py
tests/get_date_dict_property_tests.py
tests/get_datetime_dict_property_tests.py
tests/get_decimal_dict_property_tests.py
tests/get_dict_property_tests.py
tests/get_float_dict_property_tests.py
tests/get_int_dict_property_tests.py
tests/get_list_dict_property_tests.py
tests/get_required_value_tests.py
tests/get_setting_by_path_tests.py
tests/get_str_dict_property_tests.py
tests/get_value_tests.py
tests/schema_validator_tests.py
power_dict-0.0.13.dist-info/LICENSE
power_dict-0.0.13.dist-info/METADATA
power_dict-0.0.13.dist-info/WHEEL
power_dict-0.0.13.dist-info/top_level.txt
power_dict-0.0.13.dist-info/RECORD
