Metadata-Version: 2.1
Name: power-dict
Version: 0.0.13
Summary: Library for easy work with the python dictionary
Home-page: https://github.com/agorinenko/power-dict
Author: Gorinenko Anton
Author-email: anton.gorinenko@gmail.com
License: UNKNOWN
Keywords: python,dict,utils
Platform: UNKNOWN
Classifier: Programming Language :: Python :: 3.7
Classifier: Programming Language :: Python :: 3.8
Classifier: License :: OSI Approved :: MIT License
Classifier: Operating System :: OS Independent
Requires-Python: >=3.7
Requires-Dist: try-parse
